vecem/__init__.py
vecem/config.py
vecem/downloader.py
vecem-0.2.0.dist-info/METADATA
vecem-0.2.0.dist-info/WHEEL
vecem-0.2.0.dist-info/top_level.txt
vecem-0.2.0.dist-info/RECORD
